dp_greet/__init__.py
dp_greet/main.py
dp_greet-0.3.0.dist-info/entry_points.txt
dp_greet-0.3.0.dist-info/WHEEL
dp_greet-0.3.0.dist-info/METADATA
dp_greet-0.3.0.dist-info/RECORD
