Metadata-Version: 2.1
Name: dp-greet
Version: 0.3.0
Summary: 
Author: lukaszziobro89
Author-email: lukasz.ziobro.89@gmail.com
Requires-Python: >=3.10,<4.0
Classifier: Programming Language :: Python :: 3
Classifier: Programming Language :: Python :: 3.10
Classifier: Programming Language :: Python :: 3.11
Requires-Dist: typer[all] (>=0.7.0,<0.8.0)
